ultrasound_processing_package/__init__.py
ultrasound_processing_package/curved_transform.py
ultrasound_processing_package/noise_removal.py
ultrasound_processing_package-0.1.0.dist-info/METADATA
ultrasound_processing_package-0.1.0.dist-info/WHEEL
ultrasound_processing_package-0.1.0.dist-info/top_level.txt
ultrasound_processing_package-0.1.0.dist-info/RECORD
